portfoliogen/__init__.py
portfoliogen/cli.py
portfoliogen/generator.py
portfoliogen/templates/developer/index.html
portfoliogen/templates/developer/script.js
portfoliogen/templates/developer/styles.css
portfoliogen/templates/photographer/index.html
portfoliogen/templates/photographer/script.js
portfoliogen/templates/photographer/styles.css
portfoliogen-1.2.0.dist-info/licenses/LICENSE
portfoliogen-1.2.0.dist-info/METADATA
portfoliogen-1.2.0.dist-info/WHEEL
portfoliogen-1.2.0.dist-info/entry_points.txt
portfoliogen-1.2.0.dist-info/top_level.txt
portfoliogen-1.2.0.dist-info/RECORD
