Metadata-Version: 2.4
Name: portfoliogen
Version: 1.2.0
Summary: Automatic portfolio project generator
Home-page: https://github.com/sameer-lamichhane/portfolio-gen
Author: Sameer Lamichhane
Author-email: Sameer Lamichhane <sameerlamichhane00@gmail.com>
License-Expression: MIT
Project-URL: Homepage, https://github.com/sameer-lamichhane/portfolio-gen
Project-URL: Repository, https://github.com/sameer-lamichhane/portfolio-gen
Project-URL: Issues, https://github.com/sameer-lamichhane/portfolio-gen/issues
Project-URL: Documentation, https://github.com/sameer-lamichhane/portfolio-gen#readme
Keywords: portfolio,generator,html,css,javascript,web,development
Classifier: Development Status :: 4 - Beta
Classifier: Intended Audience :: Developers
Classifier: Operating System :: OS Independent
Classifier: Programming Language :: Python :: 3
Classifier: Programming Language :: Python :: 3.7
Classifier: Programming Language :: Python :: 3.8
Classifier: Programming Language :: Python :: 3.9
Classifier: Programming Language :: Python :: 3.10
Classifier: Programming Language :: Python :: 3.11
Classifier: Programming Language :: Python :: 3.12
Classifier: Topic :: Software Development :: Code Generators
Classifier: Topic :: Internet :: WWW/HTTP :: Dynamic Content
Requires-Python: >=3.7
License-File: LICENSE
Requires-Dist: importlib-resources>=1.3.0; python_version < "3.9"
Provides-Extra: dev
Requires-Dist: pytest>=6.0; extra == "dev"
Requires-Dist: black>=21.0; extra == "dev"
Requires-Dist: flake8>=3.8; extra == "dev"
Requires-Dist: twine>=3.0; extra == "dev"
Requires-Dist: build>=0.7.0; extra == "dev"
Dynamic: author
Dynamic: home-page
Dynamic: license-file
Dynamic: requires-python
